memos/__init__.py
memos/commands.py
memos/config.py
memos/crud.py
memos/default_config.yaml
memos/embedding.py
memos/logging_config.py
memos/main.py
memos/migrations.py
memos/models.py
memos/process_webp.py
memos/read_metadata.py
memos/record.py
memos/schemas.py
memos/search.py
memos/server.py
memos/service_manager.py
memos/test_server.py
memos/utils.py
memos/cmds/__init__.py
memos/cmds/library.py
memos/cmds/plugin.py
memos/databases/__init__.py
memos/databases/initializers.py
memos/migrations/alembic.ini
memos/migrations/alembic/README
memos/migrations/alembic/env.py
memos/migrations/alembic/script.py.mako
memos/migrations/alembic/versions/00904ac8c6fc_add_indexes_to_entitymodel.py
memos/migrations/alembic/versions/04acdaf75664_add_indices_to_entitytags_and_metadata.py
memos/migrations/alembic/versions/12504c5b1d3c_add_extra_columns_for_embedding.py
memos/migrations/alembic/versions/31a1ad0e10b3_add_entity_plugin_status.py
memos/migrations/alembic/versions/d10c55fbb7d2_add_index_for_entity_file_type_group_.py
memos/migrations/alembic/versions/edb8a15d51b1_fix_wrong_file_created_at.py
memos/migrations/alembic/versions/f8f158182416_add_active_app_index.py
memos/plugins/__init__.py
memos/plugins/ocr/__init__.py
memos/plugins/ocr/main.py
memos/plugins/ocr/ppocr-gpu.yaml
memos/plugins/ocr/ppocr.yaml
memos/plugins/ocr/server.py
memos/plugins/vlm/__init__.py
memos/plugins/vlm/main.py
memos/simple_tokenizer/dict/README.md
memos/simple_tokenizer/dict/hmm_model.utf8
memos/simple_tokenizer/dict/idf.utf8
memos/simple_tokenizer/dict/jieba.dict.utf8
memos/simple_tokenizer/dict/stop_words.utf8
memos/simple_tokenizer/dict/user.dict.utf8
memos/simple_tokenizer/dict/pos_dict/char_state_tab.utf8
memos/simple_tokenizer/dict/pos_dict/prob_emit.utf8
memos/simple_tokenizer/dict/pos_dict/prob_start.utf8
memos/simple_tokenizer/dict/pos_dict/prob_trans.utf8
memos/simple_tokenizer/linux/libsimple.so
memos/simple_tokenizer/macos/libsimple.dylib
memos/simple_tokenizer/windows/simple.dll
memos-0.31.0.dist-info/licenses/LICENSE
memos-0.31.0.dist-info/METADATA
memos-0.31.0.dist-info/WHEEL
memos-0.31.0.dist-info/entry_points.txt
memos-0.31.0.dist-info/top_level.txt
memos-0.31.0.dist-info/RECORD
