Metadata-Version: 2.4
Name: memos
Version: 0.31.0
Summary: A package for Pensieve (previously known as memos)
Author: arkohut
License:                                  Apache License
Project-URL: Homepage, https://github.com/arkohut/pensieve
Classifier: Programming Language :: Python :: 3
Classifier: License :: OSI Approved :: Apache Software License
Classifier: Operating System :: OS Independent
Requires-Python: >=3.10
License-File: LICENSE
Requires-Dist: fastapi
Requires-Dist: uvicorn
Requires-Dist: httpx
Requires-Dist: pydantic>=2.0
Requires-Dist: sqlalchemy>=2.0
Requires-Dist: typer>=0.13
Requires-Dist: magika
Requires-Dist: pydantic-settings>=2.6
Requires-Dist: opencv-python
Requires-Dist: pillow
Requires-Dist: piexif
Requires-Dist: imagehash
Requires-Dist: rapidocr>=2.1.0
Requires-Dist: openvino==2025.1.0; sys_platform == "win32"
Requires-Dist: onnxruntime
Requires-Dist: py-cpuinfo
Requires-Dist: psutil
Requires-Dist: pywin32; sys_platform == "win32"
Requires-Dist: pyobjc-core; sys_platform == "darwin"
Requires-Dist: pyobjc-framework-Quartz; sys_platform == "darwin"
Requires-Dist: ocrmac; sys_platform == "darwin"
Requires-Dist: sentence-transformers
Requires-Dist: torch
Requires-Dist: numpy
Requires-Dist: timm
Requires-Dist: einops
Requires-Dist: modelscope
Requires-Dist: mss
Requires-Dist: sqlite_vec>=0.1.6
Requires-Dist: watchdog
Requires-Dist: alembic
Requires-Dist: logfire[sqlalchemy]
Requires-Dist: logfire[fastapi]
Requires-Dist: jieba
Requires-Dist: tabulate
Provides-Extra: postgresql
Requires-Dist: psycopg2-binary; extra == "postgresql"
Dynamic: license-file
